airflow/__init__.py
airflow/__main__.py
airflow/alembic.ini
airflow/configuration.py
airflow/customized_form_field_behaviours.schema.json
airflow/exceptions.py
airflow/logging_config.py
airflow/plugins_manager.py
airflow/provider_info.schema.json
airflow/providers_manager.py
airflow/py.typed
airflow/sentry.py
airflow/settings.py
airflow/stats.py
airflow/templates.py
airflow/typing_compat.py
airflow/version.py
airflow/_vendor/__init__.py
airflow/_vendor/connexion/__init__.py
airflow/_vendor/connexion/__main__.py
airflow/_vendor/connexion/cli.py
airflow/_vendor/connexion/exceptions.py
airflow/_vendor/connexion/handlers.py
airflow/_vendor/connexion/http_facts.py
airflow/_vendor/connexion/json_schema.py
airflow/_vendor/connexion/jsonifier.py
airflow/_vendor/connexion/lifecycle.py
airflow/_vendor/connexion/mock.py
airflow/_vendor/connexion/options.py
airflow/_vendor/connexion/problem.py
airflow/_vendor/connexion/resolver.py
airflow/_vendor/connexion/setup.py
airflow/_vendor/connexion/spec.py
airflow/_vendor/connexion/utils.py
airflow/_vendor/connexion/apis/__init__.py
airflow/_vendor/connexion/apis/abstract.py
airflow/_vendor/connexion/apis/aiohttp_api.py
airflow/_vendor/connexion/apis/flask_api.py
airflow/_vendor/connexion/apis/flask_utils.py
airflow/_vendor/connexion/apps/__init__.py
airflow/_vendor/connexion/apps/abstract.py
airflow/_vendor/connexion/apps/aiohttp_app.py
airflow/_vendor/connexion/apps/flask_app.py
airflow/_vendor/connexion/decorators/__init__.py
airflow/_vendor/connexion/decorators/coroutine_wrappers.py
airflow/_vendor/connexion/decorators/decorator.py
airflow/_vendor/connexion/decorators/metrics.py
airflow/_vendor/connexion/decorators/parameter.py
airflow/_vendor/connexion/decorators/produces.py
airflow/_vendor/connexion/decorators/response.py
airflow/_vendor/connexion/decorators/security.py
airflow/_vendor/connexion/decorators/uri_parsing.py
airflow/_vendor/connexion/decorators/validation.py
airflow/_vendor/connexion/operations/__init__.py
smartpip2-2.1.10.dist-info/METADATA
smartpip2-2.1.10.dist-info/WHEEL
smartpip2-2.1.10.dist-info/entry_points.txt
smartpip2-2.1.10.dist-info/top_level.txt
smartpip2-2.1.10.dist-info/RECORD
